{
"SkillId": 10777,
"CastingActions": [{"Name": "L2EffectEmitter3", "AttachOn": "AM_Trail","offset": "(X=-0.700000)","bSpawnOnTarget": "False","ScaleSize": "1.300000","EffectClass": "ClassLineageEffect.d_ar_red_ca","SimpleEffectClass": "ClassLineageEffect.d_ar_red_ca_simple"}],
"ShotActions": [{"Name": "L2EffectEmitter1", "AttachOn": "AM_RH","bSpawnOnTarget": "False","bRelativeToCylinder": "False","ScaleSize": "1.200000","EffectClass": "ClassLineageEffect.d_ar_tan2_pre","SimpleEffectClass": "ClassLineageEffect.d_ar_tan2_pre_simple"},{"Name": "L2EffectEmitter0", "AttachOn": "AM_RH","bSpawnOnTarget": "False","bRelativeToCylinder": "False","ScaleSize": "1.000000","EffectClass": "ClassLineageEffect.d_ar_stunshot1_ca","SimpleEffectClass": "ClassLineageEffect.d_ar_stunshot1_ca_simple"},{"Name": "L2EffectEmitter4", "AttachOn": "AM_BoneLocation","AttachBoneName": "Bip01_R_Hand","bSpawnOnTarget": "False","bRelativeToCylinder": "False","ScaleSize": "1.000000","EffectClass": "ClassLineageEffect.d_baseTrail2_fl","SimpleEffectClass": "ClassLineageEffect.d_baseTrail2_fl_simple"}]
}
