{
"SkillId": 497,
"CastingActions": [{"Name": "L2EffectEmitter0", "AttachOn": "AM_Trail","bSpawnOnTarget": "False","ScaleSize": "0.600000","EffectClass": "ClassLineageEffect.d_mon_heal1_ca","SimpleEffectClass": "ClassLineageEffect.d_mon_heal1_ca_simple"}],
"ShotActions": [{"Name": "L2EffectEmitter3", "AttachOn": "AM_Trail","offset": "(Z=-1.000000)","bOnMultiTarget": "True","ScaleSize": "-1.000000","EffectClass": "ClassLineageEffect.d_mon_heal1_ta","SimpleEffectClass": "ClassLineageEffect.d_mon_heal1_ta_simple"}]
}
