{
"SkillId": 497,
"CastingActions": [{"Name": "L2EffectEmitter0", "AttachOn": "AM_Trail","offset": "(X=-0.550000)","bSpawnOnTarget": "False","ScaleSize": "0.650000","EffectClass": "ClassLineageEffect.d_awaken_1_deco","SimpleEffectClass": "ClassLineageEffect.d_awaken_1_deco_simple"},{"Name": "L2EffectEmitter3", "AttachOn": "AM_Trail","offset": "(X=-0.550000,Z=-1.000000)","bSpawnOnTarget": "False","ScaleSize": "1.200000","SpawnDelay": "1.200000","EffectClass": "ClassLineageEffect.d_debuff_p","SimpleEffectClass": "ClassLineageEffect.d_debuff_p_simple"}],
"ShotActions": [{"Name": "L2EffectEmitter2", "AttachOn": "AM_Trail","offset": "(Z=-0.650000)","bSpawnOnTarget": "False","ScaleSize": "0.900000","EffectClass": "ClassLineageEffect.e_u315_el_ta","SimpleEffectClass": "ClassLineageEffect.e_u315_el_ta_simple"},{"Name": "L2EffectEmitter1", "AttachOn": "AM_Trail","bOnMultiTarget": "True","ScaleSize": "-1.000000","SpawnDelay": "0.200000","EffectClass": "ClassLineageEffect.d_mon_elec1_ta","SimpleEffectClass": "ClassLineageEffect.d_mon_elec1_ta_simple"}]
}
