{
"SkillId": 19109,
"CastingActions": [{"Name": "L2EffectEmitter0", "AttachOn": "AM_Trail","offset": "(Z=-0.800000)","bSpawnOnTarget": "False","ScaleSize": "0.800000","EffectClass": "ClassLineageEffect.u_golem_sum_ca","SimpleEffectClass": "ClassLineageEffect.u_golem_sum_ca_simple"}],
"ShotActions": [{"Name": "L2EffectEmitter1", "AttachOn": "AM_Trail","offset": "(Z=-1.000000)","bSpawnOnTarget": "False","ScaleSize": "1.000000","EffectClass": "ClassLineageEffect.s_u833_transform_y","SimpleEffectClass": "ClassLineageEffect.s_u833_transform_y_simple"}]
}
