{
"SkillId": 6289,
"CastingActions": [{"Name": "L2EffectEmitter0", "AttachOn": "AM_Trail","offset": "(Z=-1.000000)","bSpawnOnTarget": "False","ScaleSize": "0.800000","EffectClass": "ClassLineageEffect.z_cast_red_ca","SimpleEffectClass": "ClassLineageEffect.z_cast_red_ca_simple"},{"Name": "L2EffectEmitter1", "AttachOn": "AM_Trail","offset": "(Z=-1.000000)","bSpawnOnTarget": "False","ScaleSize": "0.300000","SpawnDelay": "3.000000","EffectClass": "ClassLineageEffect.z_kegor_brave","SimpleEffectClass": "ClassLineageEffect.z_kegor_brave_simple"}],
"ShotActions": [{"Name": "L2EffectEmitter1", "AttachOn": "AM_Trail","offset": "(Z=-1.000000)","bSpawnOnTarget": "False","ScaleSize": "0.300000","SpawnDelay": "3.000000","EffectClass": "ClassLineageEffect.z_kegor_brave","SimpleEffectClass": "ClassLineageEffect.z_kegor_brave_simple"},{"Name": "L2EffectEmitter11", "AttachOn": "AM_Trail","offset": "(Z=-1.000000)","bOnMultiTarget": "True","EffectClass": "ClassLineageEffect.su_focus_ta","SimpleEffectClass": "ClassLineageEffect.su_focus_ta_simple"}]
}
