{
"SkillId": 1167,
"CastingActions": [{"Name": "L2EffectEmitter0", "AttachOn": "AM_Trail","offset": "(Z=-1.200000)","bSpawnOnTarget": "False","ScaleSize": "0.600000","EffectClass": "ClassLineageEffect.bl_berserker_spirit_ca","SimpleEffectClass": "ClassLineageEffect.bl_berserker_spirit_ca_simple"},{"Name": "L2EffectEmitter1", "AttachOn": "AM_Trail","offset": "(Z=-1.000000)","bSpawnOnTarget": "False","ScaleSize": "0.800000","EffectClass": "ClassLineageEffect.d_smoke_darkb","SimpleEffectClass": "ClassLineageEffect.d_smoke_darkb_simple"},{"Name": "L2EffectEmitter2", "AttachOn": "AM_Trail","offset": "(Z=-1.000000)","bSpawnOnTarget": "False","ScaleSize": "0.800000","SpawnDelay": "1.500000","EffectClass": "ClassLineageEffect.d_smoke_darkb","SimpleEffectClass": "ClassLineageEffect.d_smoke_darkb_simple"}],
"ShotActions": [{"Name": "L2EffectEmitter3", "AttachOn": "AM_Trail","offset": "(Z=-1.000000)","EffectClass": "ClassLineageEffect.bl_poison_cloud_ta","SimpleEffectClass": "ClassLineageEffect.bl_poison_cloud_ta_simple"},{"Name": "L2EffectEmitter4", "AttachOn": "AM_Trail","bOnMultiTarget": "True","EffectClass": "ClassLineageEffect.bl_curse_poison_ta","SimpleEffectClass": "ClassLineageEffect.bl_curse_poison_ta_simple"},{"Name": "L2EffectEmitter5", "AttachOn": "AM_Trail","bOnMultiTarget": "True","ScaleSize": "0.800000","EffectClass": "ClassLineageEffect.d_smoke_darkb","SimpleEffectClass": "ClassLineageEffect.d_smoke_darkb_simple"}]
}
