{
"SkillId": 9,
"CastingActions": [{"Name": "L2EffectEmitter0", "AttachOn": "AM_Trail","offset": "(Z=-1.000000)","bSpawnOnTarget": "False","EffectClass": "ClassLineageEffect.s_u010_a","SimpleEffectClass": "ClassLineageEffect.s_u010_a_simple"}],
"ShotActions": [{"Name": "L2EffectEmitter1", "AttachOn": "AM_Trail","offset": "(Z=-1.000000)","bSpawnOnTarget": "False","EffectClass": "ClassLineageEffect.el_flame_strike_ra","SimpleEffectClass": "ClassLineageEffect.el_flame_strike_ra_simple"},{"Name": "L2EffectEmitter2", "AttachOn": "AM_Trail","bOnMultiTarget": "True","EffectClass": "ClassLineageEffect.el_flame_strike_ta","SimpleEffectClass": "ClassLineageEffect.el_flame_strike_ta_simple"}]
}
